[
  {
    "task": "Acknowledge the greeting and offer assistance.",
    "tools_used": [
      "run_command"
    ],
    "outcome": "success",
    "lesson": "Successfully completed: Acknowledge the greeting and offer assistance. using strategy 'conversational response generation'",
    "timestamp": "2026-06-29T15:18:36.038728"
  },
  {
    "task": "Acknowledge greeting and prompt user for next task",
    "tools_used": [],
    "outcome": "success",
    "lesson": "Successfully completed: Acknowledge greeting and prompt user for next task",
    "timestamp": "2026-06-29T15:21:11.049195"
  },
  {
    "task": "Open the Notepad application.",
    "tools_used": [
      "open_app"
    ],
    "outcome": "success",
    "lesson": "Successfully completed: Open the Notepad application.",
    "timestamp": "2026-06-29T15:27:29.511352"
  },
  {
    "task": "Open Notepad, create a new file, and write a song about AI into it.",
    "tools_used": [
      "open_app",
      "type_text"
    ],
    "outcome": "success",
    "lesson": "Successfully completed: Open Notepad, create a new file, and write a song about AI into it. using strategy 'Open target application, sequentially input required data using type_text, and conclude with a specific writing confirmation step as requested by the hint.'",
    "timestamp": "2026-06-29T15:32:01.094005"
  },
  {
    "task": "it is to short make it long edit it",
    "tools_used": [],
    "outcome": "success",
    "lesson": "Successfully completed: it is to short make it long edit it",
    "timestamp": "2026-06-29T15:35:30.458603"
  }
]